README.md
setup.py
daemon/targetclid
scripts/targetcli
systemd/targetclid.service
systemd/targetclid.socket
targetcli/__init__.py
targetcli/ui_backstore.py
targetcli/ui_node.py
targetcli/ui_root.py
targetcli/ui_target.py
targetcli/version.py
targetcli_fb.egg-info/PKG-INFO
targetcli_fb.egg-info/SOURCES.txt
targetcli_fb.egg-info/dependency_links.txt
targetcli_fb.egg-info/top_level.txt