Metadata-Version: 1.2
Name: targetcli-fb
Version: 2.1.51.1
Summary: An administration shell for RTS storage targets.
Home-page: http://github.com/open-iscsi/targetcli-fb
Maintainer: Andy Grover
Maintainer-email: agrover@redhat.com
License: Apache 2.0
Platform: UNKNOWN
Classifier: Programming Language :: Python
Classifier: Programming Language :: Python :: 3
Classifier: License :: OSI Approved :: Apache Software License
